MANIFEST.in
setup.py
sloth/.dockerignore
sloth/Dockerfile
sloth/__init__.py
sloth/__main__.py
sloth/requirements.txt
sloth/actions/__init__.py
sloth/actions/fields.py
sloth/actions/inputs.py
sloth/api/__init__.py
sloth/api/actions.py
sloth/api/dashboard.py
sloth/api/models.py
sloth/api/urls.py
sloth/api/views.py
sloth/api/backends/__init__.py
sloth/api/exceptions/__init__.py
sloth/api/management/__init__.py
sloth/api/management/commands/__init__.py
sloth/api/management/commands/cloud.py
sloth/api/management/commands/query.py
sloth/api/management/commands/reset_passwords.py
sloth/api/management/commands/selenium.py
sloth/api/management/commands/send_web_push_notification.py
sloth/api/management/commands/startserver.py
sloth/api/management/commands/sync.py
sloth/api/management/commands/sync_roles.py
sloth/api/management/commands/test.py
sloth/api/migrations/0001_initial.py
sloth/api/migrations/0002_role_user.py
sloth/api/migrations/0003_alter_application_user.py
sloth/api/migrations/0004_task.py
sloth/api/migrations/0005_task_stopped_alter_task_message.py
sloth/api/migrations/0006_role_active_alter_role_name_alter_role_scope_key_and_more.py
sloth/api/migrations/0007_alter_scope_description_alter_task_error.py
sloth/api/migrations/0008_alter_application_available_scopes_and_more.py
sloth/api/migrations/0009_pushnotification.py
sloth/api/migrations/0010_alter_pushnotification_user.py
sloth/api/migrations/0011_alter_application_client_secret.py
sloth/api/migrations/0012_authcode.py
sloth/api/migrations/0013_task_partial_task_total.py
sloth/api/migrations/0014_email.py
sloth/api/migrations/__init__.py
sloth/api/static/css/all.min.css
sloth/api/static/css/bootstrap-icons.css
sloth/api/static/css/bootstrap.min.css
sloth/api/static/css/bpmn.css
sloth/api/static/css/colorpick.min.css
sloth/api/static/css/icons.svg
sloth/api/static/css/jquery-ui.css
sloth/api/static/css/leaflet.css
sloth/api/static/css/select2.min.css
sloth/api/static/css/sloth.css
sloth_framework.egg-info/PKG-INFO
sloth_framework.egg-info/SOURCES.txt
sloth_framework.egg-info/dependency_links.txt
sloth_framework.egg-info/requires.txt
sloth_framework.egg-info/top_level.txt