Metadata-Version: 2.1
Name: sloth-framework
Version: 0.1.13
Summary: Metadata-based web framework for the development of management information systems
Home-page: http://sloth.aplicativo.click/
Author: Breno Silva
Author-email: brenokcc@yahoo.com.br
License: BSD License
Platform: UNKNOWN
Classifier: Environment :: Web Environment
Classifier: Framework :: Django
Classifier: Intended Audience :: Developers
Classifier: License :: OSI Approved :: BSD License
Classifier: Operating System :: OS Independent
Classifier: Programming Language :: Python
Classifier: Topic :: Internet :: WWW/HTTP
Classifier: Topic :: Internet :: WWW/HTTP :: Dynamic Content
Provides-Extra: dev
Provides-Extra: production
